odoo/addons/stock_lot_remove/README.rst
odoo/addons/stock_lot_remove/__init__.py
odoo/addons/stock_lot_remove/__manifest__.py
odoo/addons/stock_lot_remove/hooks.py
odoo/addons/stock_lot_remove/data/ir_cron.xml
odoo/addons/stock_lot_remove/i18n/fr.po
odoo/addons/stock_lot_remove/i18n/stock_lot_remove.pot
odoo/addons/stock_lot_remove/models/__init__.py
odoo/addons/stock_lot_remove/models/stock_picking_type.py
odoo/addons/stock_lot_remove/models/stock_warehouse.py
odoo/addons/stock_lot_remove/readme/CONFIGURE.md
odoo/addons/stock_lot_remove/readme/CONTEXT.md
odoo/addons/stock_lot_remove/readme/CONTRIBUTORS.md
odoo/addons/stock_lot_remove/readme/CREDITS.md
odoo/addons/stock_lot_remove/readme/DESCRIPTION.md
odoo/addons/stock_lot_remove/readme/USAGE.md
odoo/addons/stock_lot_remove/security/ir.model.access.csv
odoo/addons/stock_lot_remove/static/description/icon.png
odoo/addons/stock_lot_remove/static/description/index.html
odoo/addons/stock_lot_remove/tests/__init__.py
odoo/addons/stock_lot_remove/tests/test_stock_lot_remove.py
odoo/addons/stock_lot_remove/views/stock_picking_type.xml
odoo/addons/stock_lot_remove/views/stock_warehouse.xml
odoo/addons/stock_lot_remove/wizards/__init__.py
odoo/addons/stock_lot_remove/wizards/stock_lot_removal_wizard.py
odoo/addons/stock_lot_remove/wizards/stock_lot_removal_wizard.xml
odoo_addon_stock_lot_remove-16.0.1.0.0.2.dist-info/METADATA
odoo_addon_stock_lot_remove-16.0.1.0.0.2.dist-info/WHEEL
odoo_addon_stock_lot_remove-16.0.1.0.0.2.dist-info/top_level.txt
odoo_addon_stock_lot_remove-16.0.1.0.0.2.dist-info/RECORD
