Metadata-Version: 2.1
Name: odoo-addon-stock_lot_remove
Version: 16.0.1.0.0.2
Summary: Automatically move remaining quants with a past removal date out " "of your stock
Home-page: https://github.com/OCA/stock-logistics-workflow
Author: ACSONE SA/NV,BCIM,Odoo Community Association (OCA)
Author-email: support@odoo-community.org
License: AGPL-3
Classifier: Programming Language :: Python
Classifier: Framework :: Odoo
Classifier: Framework :: Odoo :: 16.0
Classifier: License :: OSI Approved :: GNU Affero General Public License v3
Requires-Python: >=3.10
Requires-Dist: odoo<16.1dev,>=16.0a
